[
  {
    "id": "EUR/USD_1766132680",
    "pair": "EUR/USD",
    "direction": "BUY",
    "entry_price": 1.171,
    "sl": 1.1603501145499093,
    "tp": 1.186974828175136,
    "created_at": "2025-12-19T08:24:40.325914+00:00",
    "expires_at": "2025-12-19T12:24:40.325914+00:00",
    "status": "ACTIVE",
    "confidence": 0.95,
    "strategy": "MEAN_REVERSION",
    "indicators": {
      "rsi": 71.31310030914032,
      "adx": 37.601434858235656,
      "macd_histogram": 0.0010554692970042119,
      "stochastic_k": 58.96810738980608,
      "bb_position": 0.7269212516853242,
      "ema12": 1.169890576729005,
      "ema26": 1.1659448524009437,
      "ema200": 1.1460339842179783
    },
    "patterns": [],
    "confidence_factors": [
      "Strong uptrend (EMA 12>26>50)",
      "Above 200 EMA (long-term bull)",
      "Price near upper Bollinger (reversal)",
      "ADX trend strength (37.6)"
    ],
    "scores": {
      "bullish": 55,
      "bearish": 20,
      "edge": 35
    },
    "sentiment": {
      "score": 0.0,
      "positive_count": 0,
      "negative_count": 0,
      "relevant_news": [
        {
          "title": "USD: Amplified Exposure To The Semiconductor Industry (NYSEARCA:USD)",
          "sentiment": "neutral",
          "published": "2025-11-17T21:24:15.000000Z",
          "source": "seekingalpha.com"
        },
        {
          "title": "Is ProShares Ultra Semiconductors (USD) the Best Performing ETF of the Last 5 Years?",
          "sentiment": "neutral",
          "published": "2025-02-23T03:55:49.000000Z",
          "source": "insidermonkey.com"
        },
        {
          "title": "USD: Capitalizing On AI And Semiconductor Growth With 2x Leverage (NYSEARCA:USD)",
          "sentiment": "neutral",
          "published": "2025-02-01T12:43:33.000000Z",
          "source": "seekingalpha.com"
        }
      ],
      "total_news": 3,
      "api_calls_used": "17/90"
    },
    "news_context": {
      "relevant_news_count": 3,
      "sentiment_score": 0.0
    },
    "outcome": null,
    "outcome_time": null,
    "outcome_pips": 0.0
  },
  {
    "id": "AUD/USD_1766132728",
    "pair": "AUD/USD",
    "direction": "BUY",
    "entry_price": 0.6604,
    "sl": 0.6525115636825561,
    "tp": 0.6722326544761658,
    "created_at": "2025-12-19T08:25:28.417983+00:00",
    "expires_at": "2025-12-19T12:25:28.417983+00:00",
    "status": "ACTIVE",
    "confidence": 0.9199999999999999,
    "strategy": "TREND_FOLLOWING",
    "indicators": {
      "rsi": 61.9409804113451,
      "adx": 56.12967752529626,
      "macd_histogram": -4.263341240207542e-05,
      "stochastic_k": 48.2090831922127,
      "bb_position": 0.5790083189566106,
      "ema12": 0.6615452746238164,
      "ema26": 0.6587835981095731,
      "ema200": 0.6517150783269668
    },
    "patterns": [],
    "confidence_factors": [
      "Strong uptrend (EMA 12>26>50)",
      "Above 200 EMA (long-term bull)",
      "RSI bearish zone (61.9)",
      "ADX trend strength (56.1)"
    ],
    "scores": {
      "bullish": 50,
      "bearish": 20,
      "edge": 30
    },
    "sentiment": {
      "score": 0.0,
      "positive_count": 0,
      "negative_count": 0,
      "relevant_news": [
        {
          "title": "USD: Amplified Exposure To The Semiconductor Industry (NYSEARCA:USD)",
          "sentiment": "neutral",
          "published": "2025-11-17T21:24:15.000000Z",
          "source": "seekingalpha.com"
        },
        {
          "title": "Is ProShares Ultra Semiconductors (USD) the Best Performing ETF of the Last 5 Years?",
          "sentiment": "neutral",
          "published": "2025-02-23T03:55:49.000000Z",
          "source": "insidermonkey.com"
        },
        {
          "title": "USD: Capitalizing On AI And Semiconductor Growth With 2x Leverage (NYSEARCA:USD)",
          "sentiment": "neutral",
          "published": "2025-02-01T12:43:33.000000Z",
          "source": "seekingalpha.com"
        }
      ],
      "total_news": 3,
      "api_calls_used": "17/90"
    },
    "news_context": {
      "relevant_news_count": 3,
      "sentiment_score": 0.0
    },
    "outcome": null,
    "outcome_time": null,
    "outcome_pips": 0.0
  },
  {
    "id": "USD/CAD_1766132743",
    "pair": "USD/CAD",
    "direction": "SELL",
    "entry_price": 1.379,
    "sl": 1.3905714073181152,
    "tp": 1.3616428890228272,
    "created_at": "2025-12-19T08:25:43.824557+00:00",
    "expires_at": "2025-12-19T12:25:43.824557+00:00",
    "status": "ACTIVE",
    "confidence": 0.8866666666666666,
    "strategy": "MEAN_REVERSION",
    "indicators": {
      "rsi": 24.837400811925406,
      "adx": 55.14595875660013,
      "macd_histogram": -0.0013498379611140707,
      "stochastic_k": 21.466148984805702,
      "bb_position": 0.26501504661635256,
      "ema12": 1.3828064453212188,
      "ema26": 1.3894559381076892,
      "ema200": 1.391106387277661
    },
    "patterns": [],
    "confidence_factors": [
      "Strong downtrend (EMA 12<26<50)",
      "Below 200 EMA (long-term bear)",
      "Stochastic bullish crossover",
      "Price near lower Bollinger (reversal)",
      "ADX trend strength (55.1)"
    ],
    "scores": {
      "bullish": 30,
      "bearish": 55,
      "edge": 25
    },
    "sentiment": {
      "score": 0.0,
      "positive_count": 0,
      "negative_count": 0,
      "relevant_news": [
        {
          "title": "USD: Amplified Exposure To The Semiconductor Industry (NYSEARCA:USD)",
          "sentiment": "neutral",
          "published": "2025-11-17T21:24:15.000000Z",
          "source": "seekingalpha.com"
        },
        {
          "title": "Is ProShares Ultra Semiconductors (USD) the Best Performing ETF of the Last 5 Years?",
          "sentiment": "neutral",
          "published": "2025-02-23T03:55:49.000000Z",
          "source": "insidermonkey.com"
        },
        {
          "title": "USD: Capitalizing On AI And Semiconductor Growth With 2x Leverage (NYSEARCA:USD)",
          "sentiment": "neutral",
          "published": "2025-02-01T12:43:33.000000Z",
          "source": "seekingalpha.com"
        }
      ],
      "total_news": 3,
      "api_calls_used": "17/90"
    },
    "news_context": {
      "relevant_news_count": 3,
      "sentiment_score": 0.0
    },
    "outcome": null,
    "outcome_time": null,
    "outcome_pips": 0.0
  },
  {
    "id": "EUR/USD_1766132776",
    "pair": "EUR/USD",
    "direction": "BUY",
    "entry_price": 1.1718,
    "sl": 1.1611501145499092,
    "tp": 1.187774828175136,
    "created_at": "2025-12-19T08:26:16.721470+00:00",
    "expires_at": "2025-12-19T12:26:16.721470+00:00",
    "status": "ACTIVE",
    "confidence": 0.95,
    "strategy": "MEAN_REVERSION",
    "indicators": {
      "rsi": 71.31310030914032,
      "adx": 37.601434858235656,
      "macd_histogram": 0.0010554692970042119,
      "stochastic_k": 58.96810738980608,
      "bb_position": 0.7269212516853242,
      "ema12": 1.169890576729005,
      "ema26": 1.1659448524009437,
      "ema200": 1.1460339842179783
    },
    "patterns": [],
    "confidence_factors": [
      "Strong uptrend (EMA 12>26>50)",
      "Above 200 EMA (long-term bull)",
      "Price near upper Bollinger (reversal)",
      "ADX trend strength (37.6)"
    ],
    "scores": {
      "bullish": 55,
      "bearish": 20,
      "edge": 35
    },
    "sentiment": {
      "score": 0.0,
      "positive_count": 0,
      "negative_count": 0,
      "relevant_news": [
        {
          "title": "USD: Amplified Exposure To The Semiconductor Industry (NYSEARCA:USD)",
          "sentiment": "neutral",
          "published": "2025-11-17T21:24:15.000000Z",
          "source": "seekingalpha.com"
        },
        {
          "title": "Is ProShares Ultra Semiconductors (USD) the Best Performing ETF of the Last 5 Years?",
          "sentiment": "neutral",
          "published": "2025-02-23T03:55:49.000000Z",
          "source": "insidermonkey.com"
        },
        {
          "title": "USD: Capitalizing On AI And Semiconductor Growth With 2x Leverage (NYSEARCA:USD)",
          "sentiment": "neutral",
          "published": "2025-02-01T12:43:33.000000Z",
          "source": "seekingalpha.com"
        }
      ],
      "total_news": 3,
      "api_calls_used": "17/90"
    },
    "news_context": {
      "relevant_news_count": 3,
      "sentiment_score": 0.0
    },
    "outcome": null,
    "outcome_time": null,
    "outcome_pips": 0.0
  },
  {
    "id": "AUD/USD_1766132823",
    "pair": "AUD/USD",
    "direction": "BUY",
    "entry_price": 0.6604,
    "sl": 0.6525115636825561,
    "tp": 0.6722326544761658,
    "created_at": "2025-12-19T08:27:03.995697+00:00",
    "expires_at": "2025-12-19T12:27:03.995697+00:00",
    "status": "ACTIVE",
    "confidence": 0.9199999999999999,
    "strategy": "TREND_FOLLOWING",
    "indicators": {
      "rsi": 61.9409804113451,
      "adx": 56.12967752529626,
      "macd_histogram": -4.263341240207542e-05,
      "stochastic_k": 48.2090831922127,
      "bb_position": 0.5790083189566106,
      "ema12": 0.6615452746238164,
      "ema26": 0.6587835981095731,
      "ema200": 0.6517150783269668
    },
    "patterns": [],
    "confidence_factors": [
      "Strong uptrend (EMA 12>26>50)",
      "Above 200 EMA (long-term bull)",
      "RSI bearish zone (61.9)",
      "ADX trend strength (56.1)"
    ],
    "scores": {
      "bullish": 50,
      "bearish": 20,
      "edge": 30
    },
    "sentiment": {
      "score": 0.0,
      "positive_count": 0,
      "negative_count": 0,
      "relevant_news": [
        {
          "title": "USD: Amplified Exposure To The Semiconductor Industry (NYSEARCA:USD)",
          "sentiment": "neutral",
          "published": "2025-11-17T21:24:15.000000Z",
          "source": "seekingalpha.com"
        },
        {
          "title": "Is ProShares Ultra Semiconductors (USD) the Best Performing ETF of the Last 5 Years?",
          "sentiment": "neutral",
          "published": "2025-02-23T03:55:49.000000Z",
          "source": "insidermonkey.com"
        },
        {
          "title": "USD: Capitalizing On AI And Semiconductor Growth With 2x Leverage (NYSEARCA:USD)",
          "sentiment": "neutral",
          "published": "2025-02-01T12:43:33.000000Z",
          "source": "seekingalpha.com"
        }
      ],
      "total_news": 3,
      "api_calls_used": "17/90"
    },
    "news_context": {
      "relevant_news_count": 3,
      "sentiment_score": 0.0
    },
    "outcome": null,
    "outcome_time": null,
    "outcome_pips": 0.0
  }
]