{
  "timestamp": "2025-11-27T03:07:50.134066+00:00",
  "iteration": 8,
  "version": "v20.1-optimized",
  "mode": "LIVE_TRADING",
  "signals": {
    "EUR/USD": {
      "direction": "SELL",
      "last_price": 1.16,
      "SL": 1.1605524621691021,
      "TP": 1.159309422288622,
      "confidence": 18.973166108747524,
      "threshold": 10.0,
      "rb_epsilon": 0.7,
      "timestamp": "2025-11-27T03:07:50.118386+00:00"
    },
    "GBP/USD": {
      "direction": "SELL",
      "last_price": 1.325,
      "SL": 1.3251973833356583,
      "TP": 1.324753270830427,
      "confidence": 18.5420640322396,
      "threshold": 10.0,
      "rb_epsilon": 0.7,
      "timestamp": "2025-11-27T03:07:50.123911+00:00"
    },
    "USD/JPY": {
      "direction": "SELL",
      "last_price": 156.12,
      "SL": 156.43013776506697,
      "TP": 155.7323277936663,
      "confidence": 29.112376688238996,
      "threshold": 10.0,
      "rb_epsilon": 0.7,
      "timestamp": "2025-11-27T03:07:50.128990+00:00"
    },
    "AUD/USD": {
      "direction": "SELL",
      "last_price": 0.653,
      "SL": 0.6540440430641175,
      "TP": 0.6516949461698532,
      "confidence": 24.83989262753809,
      "threshold": 10.0,
      "rb_epsilon": 0.7,
      "timestamp": "2025-11-27T03:07:50.134056+00:00"
    }
  },
  "rl_stats": {
    "total_updates": 0,
    "total_trades": 0,
    "profitable_trades": 0,
    "total_pnl": 0.0,
    "win_rate": 0.0,
    "avg_reward": 0.0,
    "epsilon_history": [],
    "q_value_history": [],
    "pipeline_trades_learned": 0,
    "last_pipeline_sync": null,
    "rbed_milestones": [],
    "consecutive_losses": 0
  },
  "active_trades": 2,
  "pipeline_stats": {
    "total_trades": 0,
    "wins": 0,
    "total_pnl": 0.0,
    "avg_pnl": 0.0,
    "win_rate": 0.0,
    "last_trade": null
  }
}