{
  "timestamp": "2025-10-09T22:53:53.752836",
  "pairs": {
    "EUR/USD": {
      "direction": "BUY",
      "strength": 0.002152452334403032,
      "score_1_100": 13,
      "last_price": 0.31740081224617334,
      "SL": 0.18779285299006623,
      "TP": 0.7142962886176409,
      "high_confidence": false
    },
    "GBP/USD": {
      "direction": "SELL",
      "strength": -0.003663285385388504,
      "score_1_100": 18,
      "last_price": 0.2627277534733907,
      "SL": 0.376147229941708,
      "TP": -0.08459410392692251,
      "high_confidence": false
    },
    "USD/JPY": {
      "direction": "BUY",
      "strength": 0.014941697621622896,
      "score_1_100": 25,
      "last_price": 0.8963386194029852,
      "SL": 0.6513794309936157,
      "TP": 1.6464715150470743,
      "high_confidence": false
    },
    "AUD/USD": {
      "direction": "BUY",
      "strength": 0.007076405676788373,
      "score_1_100": 30,
      "last_price": 0.17111899869232206,
      "SL": 0.08727437676343831,
      "TP": 0.42787445840828753,
      "high_confidence": false
    }
  }
}