{
  "timestamp": "2025-11-21T22:57:21.371717+00:00",
  "iteration": 5,
  "version": "v15.1-improved-confidence",
  "mode": "REINFORCEMENT_LEARNING",
  "signals": {
    "EUR/USD": {
      "direction": "SELL",
      "last_price": 1.151,
      "SL": 1.1536546919686455,
      "TP": 1.147017962047032,
      "confidence": 68.34861459791638,
      "threshold": 35.0,
      "q_spread": 1.1473712677365406,
      "training_progress": 0.0,
      "timestamp": "2025-11-21T22:57:21.345053+00:00",
      "q_values": [
        -1.5332570374226755,
        0.8548616468396428,
        -0.2925096208968979
      ],
      "epsilon": 1.0
    },
    "GBP/USD": {
      "direction": "SELL",
      "last_price": 1.309,
      "SL": 1.309951990536281,
      "TP": 1.3075720141955782,
      "confidence": 71.64737313727177,
      "threshold": 35.0,
      "q_spread": 1.3457301888277373,
      "training_progress": 0.0,
      "timestamp": "2025-11-21T22:57:21.353736+00:00",
      "q_values": [
        -1.2409687273498322,
        0.9027342111357273,
        -0.4429959776920101
      ],
      "epsilon": 1.0
    },
    "USD/JPY": {
      "direction": "SELL",
      "last_price": 156.37,
      "SL": 156.49228742327008,
      "TP": 156.18656886509487,
      "confidence": 87.57154843126423,
      "threshold": 35.0,
      "q_spread": 2.1992654947222117,
      "training_progress": 0.0,
      "timestamp": "2025-11-21T22:57:21.362957+00:00",
      "q_values": [
        -2.2706086459539443,
        1.460662940874396,
        -0.7386025538478155
      ],
      "epsilon": 1.0
    },
    "AUD/USD": {
      "direction": "SELL",
      "last_price": 0.6453,
      "SL": 0.6455054176194327,
      "TP": 0.6449918735708509,
      "confidence": 64.95270227442215,
      "threshold": 35.0,
      "q_spread": 0.9917726426585117,
      "training_progress": 0.0,
      "timestamp": "2025-11-21T22:57:21.371621+00:00",
      "q_values": [
        -1.722021230504623,
        0.896789929119563,
        -0.09498271353894874
      ],
      "epsilon": 1.0
    }
  },
  "rl_stats": {
    "total_updates": 0,
    "total_trades": 0,
    "profitable_trades": 0,
    "total_pnl": 0.0,
    "win_rate": 0.0,
    "avg_reward": 0.0,
    "epsilon_history": [],
    "loss_history": [],
    "q_value_history": []
  },
  "active_trades": 2,
  "total_learned_trades": 0
}